openmht/__init__.py
openmht/__main__.py
openmht/cli.py
openmht/graph.py
openmht/kalman_filter.py
openmht/mht.py
openmht/plot_tracks.py
openmht/weighted_graph.py
tests/__init__.py
tests/test_general.py
openmht-2.0.1.dist-info/LICENSE
openmht-2.0.1.dist-info/METADATA
openmht-2.0.1.dist-info/WHEEL
openmht-2.0.1.dist-info/entry_points.txt
openmht-2.0.1.dist-info/top_level.txt
openmht-2.0.1.dist-info/RECORD
