Metadata-Version: 2.1
Name: openmht
Version: 2.0.1
Summary: OpenMHT
Home-page: https://github.com/jonperdomo/openmht
Author: Jonathan Elliot Perdomo
Author-email: jonperdomodb@gmail.com
Classifier: Programming Language :: Python :: 3
Classifier: License :: OSI Approved :: GNU Affero General Public License v3
Classifier: Operating System :: OS Independent
Requires-Python: >=3.6
License-File: LICENSE
